[
  {
    "osf_id": "fm9vz_v3",
    "title": "Model-based evidence for task-dependent representations in psychological similarity and working memory",
    "date_created": "2026-07-02T01:37:47.922039",
    "date_modified": "2026-07-02T20:43:16.765405",
    "description": "A central question in visual working memory (VWM) is what psychological representation underlies performance. Standard measurement models assume recall error spreads over the physical stimulus space (e.g., a von Mises distribution on a color wheel), whereas the Target Confusability Competition model (Schurgin et al., 2020) proposes that error should instead be scaled by psychophysical similarity. Recent replications, however, find little benefit from similarity-based adjustments to VWM models (Oberauer, 2023; Tomić &amp; Bays, 2024). One limitation of this debate is that similarity is often treated as a separate input—measured in an independent task or approximated parametrically—rather than inferred jointly with the cognitive processes that generate behavior. We address this limitation by developing Bayesian generative models that infer latent stimulus representations of oriented lines based on responses in perceptual reproduction, memory reproduction, and similarity comparison tasks (Tomić &amp; Bays, 2024). The inferred representations deviate systematically from physical orientation, but in task-dependent ways: reproduction tasks show a bias towards the vertical meridian, whereas similarity judgments show attraction toward the cardinal orientations. Using Bayesian model comparison, we find that the task-specific representations provide a better explanation than a common-cause model that assumes a shared representation. This indicates mental representations should be modeled as part of task-specific generative processes, not assumed from similarity judgments alone. We conclude by highlighting two future research directions: attempting to unify our task-specific representations with additional cognitive processes, or attempting to catalog families of task-dependent representations by exploring different cognitive process models.",
    "doi": "",
    "preprint_doi": "",
    "subjects": [
      [
        {
          "id": "5b4e7425c6983001430b6c1e",
          "text": "Social and Behavioral Sciences"
        },
        {
          "id": "5b4e7426c6983001430b6c41",
          "text": "Quantitative Methods"
        },
        {
          "id": "5b4e7426c6983001430b6c4e",
          "text": "Mathematical Psychology"
        }
      ],
      [
        {
          "id": "5b4e7425c6983001430b6c1e",
          "text": "Social and Behavioral Sciences"
        },
        {
          "id": "5b4e7426c6983001430b6c41",
          "text": "Quantitative Methods"
        },
        {
          "id": "5b4e7426c6983001430b6c55",
          "text": "Computational Modeling"
        }
      ],
      [
        {
          "id": "5b4e7425c6983001430b6c1e",
          "text": "Social and Behavioral Sciences"
        },
        {
          "id": "5b4e7427c6983001430b6c71",
          "text": "Perception"
        }
      ],
      [
        {
          "id": "5b4e7425c6983001430b6c1e",
          "text": "Social and Behavioral Sciences"
        },
        {
          "id": "5b4e7427c6983001430b6c8c",
          "text": "Cognitive Psychology"
        },
        {
          "id": "5b4e7427c6983001430b6ca5",
          "text": "Memory"
        }
      ],
      [
        {
          "id": "5b4e7425c6983001430b6c1e",
          "text": "Social and Behavioral Sciences"
        },
        {
          "id": "5b4e7427c6983001430b6c8c",
          "text": "Cognitive Psychology"
        },
        {
          "id": "5b4e7429c6983001430b6cfe",
          "text": "Concepts and Categories"
        }
      ]
    ],
    "link": "https://osf.io/preprints/psyarxiv/fm9vz_v3/"
  },
  {
    "osf_id": "me6z3_v1",
    "title": "Empathy shapes multimodal child-directed communication and children’s language comprehension",
    "date_created": "2026-07-02T01:38:41.416808",
    "date_modified": "2026-07-02T20:39:27.055826",
    "description": "Effective communication requires speakers to tailor what they say, and how they say it, to their audience. Empathy may support this process, but it remains unclear whether empathic speakers adapt multimodal signals (speech, prosody, and gesture) in ways that benefit recipient understanding. We examined this question in child-directed communication. In Experiment 1, 46 broadcast-trained Chinese speakers produced semi-spontaneous programmes for child and adult audiences. Higher-empathy speakers showed stronger child-directed adaptation across lexical–syntactic, prosodic and gestural channels, including more audience-oriented lexical choices, enhanced pitch modulation, and more frequent and salient representational gestures. In Experiment 2, 221 children (7–11 years) viewed a subset of these materials from Experiment 1 for a comprehension task. Children understood child-directed programmes better when they were produced by higher-empathetic speakers, whereas empathy-related differences were minimal for adult-directed programmes. Cross-experimental mediation analyses showed that stimulus-level multimodal cues accounted for part of the association between speakers’ empathy and children’s comprehension. This indirect association was positive in child-directed programmes but negative in adult-directed programmes, indicating that empathy benefits children’s comprehension when speakers’ adaptations are aligned with children’s needs. These findings suggest that empathy operates as a higher-order communicative capacity, shaping audience-specific multimodal behaviour with consequences for children’s understanding.",
    "doi": "",
    "preprint_doi": "",
    "subjects": [
      [
        {
          "id": "5b4e7425c6983001430b6c1e",
          "text": "Social and Behavioral Sciences"
        },
        {
          "id": "5b4e7425c6983001430b6c2d",
          "text": "Developmental Psychology"
        },
        {
          "id": "5b4e7425c6983001430b6c31",
          "text": "Middle & Late Childhood"
        }
      ],
      [
        {
          "id": "5b4e7425c6983001430b6c1e",
          "text": "Social and Behavioral Sciences"
        },
        {
          "id": "5b4e7425c6983001430b6c34",
          "text": "Social and Personality Psychology"
        },
        {
          "id": "5b4e7426c6983001430b6c53",
          "text": "Individual Differences"
        }
      ],
      [
        {
          "id": "5b4e7425c6983001430b6c1e",
          "text": "Social and Behavioral Sciences"
        },
        {
          "id": "5b4e7425c6983001430b6c2d",
          "text": "Developmental Psychology"
        },
        {
          "id": "5b4e7426c6983001430b6c63",
          "text": "Cognitive Development"
        }
      ],
      [
        {
          "id": "5b4e7425c6983001430b6c1e",
          "text": "Social and Behavioral Sciences"
        },
        {
          "id": "5b4e7425c6983001430b6c34",
          "text": "Social and Personality Psychology"
        },
        {
          "id": "5b4e7427c6983001430b6c6d",
          "text": "Social Cognition"
        }
      ],
      [
        {
          "id": "5b4e7425c6983001430b6c1e",
          "text": "Social and Behavioral Sciences"
        },
        {
          "id": "5b4e7425c6983001430b6c2d",
          "text": "Developmental Psychology"
        },
        {
          "id": "5b4e7427c6983001430b6c87",
          "text": "Language Aquisition"
        }
      ],
      [
        {
          "id": "5b4e7425c6983001430b6c1e",
          "text": "Social and Behavioral Sciences"
        },
        {
          "id": "5b4e7427c6983001430b6c8b",
          "text": "Educational Psychology"
        }
      ],
      [
        {
          "id": "5b4e7425c6983001430b6c1e",
          "text": "Social and Behavioral Sciences"
        },
        {
          "id": "5b4e7427c6983001430b6c8c",
          "text": "Cognitive Psychology"
        },
        {
          "id": "5b4e7429c6983001430b6cea",
          "text": "Learning"
        }
      ],
      [
        {
          "id": "5b4e7425c6983001430b6c1e",
          "text": "Social and Behavioral Sciences"
        },
        {
          "id": "5b4e7427c6983001430b6c8c",
          "text": "Cognitive Psychology"
        },
        {
          "id": "5b4e7429c6983001430b6d01",
          "text": "Language"
        }
      ]
    ],
    "link": "https://osf.io/preprints/psyarxiv/me6z3_v1/"
  },
  {
    "osf_id": "632re_v1",
    "title": "Researchers in the behavioural and brain sciences can use e-values to safely optionally stop during data collection",
    "date_created": "2026-07-02T03:19:37.550633",
    "date_modified": "2026-07-02T20:38:38.482581",
    "description": "This paper is about a central problem facing researchers in the behavioural and brain sciences: limited resources constrain the amount of data we can collect. To address this familiar concern, we describe a new method for monitoring evidence during data collection to prevent wasted effort and resources. An emerging statistical framework called safe statistics, or anytime-valid inference, provides a statistically valid way to optionally stop (or continue) data collection. Before we describe this new framework, we briefly consider a few existing alternatives aimed at solving the same problems including group sequential designs and sequential Bayesian statistics. We point to other reviews of these approaches and discuss some reasons why uptake among behavioural and brain scientists has been limited. We then make the case that the safe statistics framework is well-suited to some of the common challenges that researchers face. We show how the framework works in a set of case studies and discuss its current limitations. We also provide code researchers can use from the safestats R package along with a companion shiny application to help the interested reader get started.",
    "doi": "",
    "preprint_doi": "",
    "subjects": [
      [
        {
          "id": "5b4e7425c6983001430b6c1e",
          "text": "Social and Behavioral Sciences"
        },
        {
          "id": "5b4e7426c6983001430b6c41",
          "text": "Quantitative Methods"
        },
        {
          "id": "5b4e7427c6983001430b6c92",
          "text": "Statistical Methods"
        }
      ]
    ],
    "link": "https://osf.io/preprints/psyarxiv/632re_v1/"
  },
  {
    "osf_id": "2jekz_v1",
    "title": "Comments on “Animal personality is a class of variation not a set of traits” by Réale, Dall, and Dingemanse (2026). Praise, and a pathway for integrating the study of personality evolution",
    "date_created": "2026-07-02T05:46:03.905837",
    "date_modified": "2026-07-02T20:35:25.936097",
    "description": "Réale, Dall, and Dingemanse have contributed a valuable commentary, both in terms of clarifying how to (and not to) consider “personality traits” and in, perhaps unknowingly, providing a glimmer of a bridge that can unify the study of animal and human personality. My comments reveal the bridge in all its glory.",
    "doi": "",
    "preprint_doi": "",
    "subjects": [
      [
        {
          "id": "5b4e7425c6983001430b6c21",
          "text": "Life Sciences"
        }
      ],
      [
        {
          "id": "5b4e7425c6983001430b6c1e",
          "text": "Social and Behavioral Sciences"
        },
        {
          "id": "5b4e7426c6983001430b6c41",
          "text": "Quantitative Methods"
        }
      ],
      [
        {
          "id": "5b4e7425c6983001430b6c1e",
          "text": "Social and Behavioral Sciences"
        },
        {
          "id": "5b4e7425c6983001430b6c34",
          "text": "Social and Personality Psychology"
        },
        {
          "id": "5b4e7426c6983001430b6c53",
          "text": "Individual Differences"
        }
      ],
      [
        {
          "id": "5b4e7425c6983001430b6c1e",
          "text": "Social and Behavioral Sciences"
        },
        {
          "id": "5b4e7427c6983001430b6c7e",
          "text": "Animal Learning and Behavior"
        }
      ],
      [
        {
          "id": "5b4e7425c6983001430b6c1e",
          "text": "Social and Behavioral Sciences"
        },
        {
          "id": "5b4e7427c6983001430b6ca0",
          "text": "Evolution"
        }
      ],
      [
        {
          "id": "5b4e7425c6983001430b6c1e",
          "text": "Social and Behavioral Sciences"
        },
        {
          "id": "5b4e7425c6983001430b6c34",
          "text": "Social and Personality Psychology"
        },
        {
          "id": "5b4e7428c6983001430b6cdf",
          "text": "Personality and Situations"
        }
      ]
    ],
    "link": "https://osf.io/preprints/psyarxiv/2jekz_v1/"
  },
  {
    "osf_id": "nzjhu_v2",
    "title": "Inference of light-source positions and of transparency in brightness illusion displays (Digital Typeset Edition)",
    "date_created": "2026-07-02T05:57:27.580729",
    "date_modified": "2026-07-02T20:34:42.507753",
    "description": "Although many researchers have attempted to explain brightness illusions, no consensus agreement has yet been reached.  I here report that two factors are essential to the study of brightness illusions, and propose a Helmholtzian explanation for the illusions based on differences of logical interpretations for the displays.  The factors that there are: (1) a possibility that our visual system unconsciously infers three light-source positions for segments in the displays (the front of the segments, the segments themselves, and the area behind the segments) and (2) a possibility that our visual system interprets a non-transparent achromatic segment not only as a non-transparent surface illuminated from the side, but also as a transparent segment illuminated from behind, a shade, a cast shadow, a self-luminous segment, or a space.  If our visual system take the factors into account and selects the more likely interpretations out of possible interpretations, it is unsurprising that segments that are physically identical gray is perceived as a different brightness in each situation.",
    "doi": "",
    "preprint_doi": "",
    "subjects": [
      [
        {
          "id": "5b4e7425c6983001430b6c1e",
          "text": "Social and Behavioral Sciences"
        },
        {
          "id": "5b4e7427c6983001430b6c71",
          "text": "Perception"
        }
      ],
      [
        {
          "id": "5b4e7425c6983001430b6c1e",
          "text": "Social and Behavioral Sciences"
        },
        {
          "id": "5b4e7427c6983001430b6c8c",
          "text": "Cognitive Psychology"
        }
      ]
    ],
    "link": "https://osf.io/preprints/psyarxiv/nzjhu_v2/"
  },
  {
    "osf_id": "ds7yj_v3",
    "title": "The Relationship Between Trauma Type, Coping Style, and Posttraumatic Symptomatology: A Retrospective Online Study",
    "date_created": "2026-07-02T06:12:44.287344",
    "date_modified": "2026-07-02T20:34:03.893283",
    "description": "Background: Previous research has shown that interpersonal trauma is associated with higher rates of posttraumatic stress symptoms, with coping responses playing a vital role in individual differences in symptom presentation. The present online study examined differential associations between trauma type, coping styles, and trauma-related symptomatology to deepen understanding of variation in trauma-related symptomatology.\nMethods: The sample included N = 300 participants who reported a traumatic life event within the past 18 months, assessed with the Life Events Checklist for DSM-5 (LEC-5). Events were classified into interpersonal and non-interpersonal trauma. Participants completed retrospective questions assessing posttraumatic coping strategies, current levels of posttraumatic stress symptoms, depression, anxiety, stress, and life satisfaction.\nResults: The present study reports secondary analyses. Correlational analyses within both trauma groups revealed positive relationships between avoidant coping and trauma-related symptoms. Group comparisons revealed higher levels of trauma-related symptoms, lower life satisfaction, and greater use of avoidant coping strategies in the interpersonal trauma group compared to the non-interpersonal trauma group. Furthermore, avoidant coping explained a significant proportion of variance in posttraumatic stress symptoms within both trauma groups, and trauma type itself accounted for significant unique variance in posttraumatic stress symptoms across the entire sample. Finally, exploratory mediation analyses provided evidence consistent with a partial mediation of the association between trauma type and posttraumatic stress symptoms.\nConclusions: These findings suggest that avoidant coping may be an important factor in understanding differences in trauma-related symptoms across trauma types. The results also point to potential intervention and prevention targets that should be evaluated in longitudinal research.",
    "doi": "",
    "preprint_doi": "",
    "subjects": [
      [
        {
          "id": "5b4e7425c6983001430b6c1e",
          "text": "Social and Behavioral Sciences"
        },
        {
          "id": "5b4e7425c6983001430b6c1f",
          "text": "Clinical Psychology"
        }
      ]
    ],
    "link": "https://osf.io/preprints/psyarxiv/ds7yj_v3/"
  },
  {
    "osf_id": "q7byw_v2",
    "title": "Principled Default Priors for Bayesian Hypothesis Testing in Binomial GLMs:   A Matched-Prior Framework with Empirical Evaluation",
    "date_created": "2026-07-02T11:36:34.482979",
    "date_modified": "2026-07-03T10:19:18.479688",
    "description": "Researchers using Bayesian hypothesis testing in binomial generalized linear models (GLMs; for instance, logistic regression for accuracy data) need priors on regression coefficients, but no widely adopted default framework exists. The nonlinear link function creates a prior-link interaction: priors that appear reasonable on the coefficient scale can imply implausible distributions on the probability scale. We show that this problem has an exact solution for CDF-based link functions: matched priors – prior families whose CDF mirrors the link function – produce uniform distributions on the probability scale for the intercept, a maximally uninformative anchor. We extend this family choice to effect priors for parsimony, with prior scale determined via prior predictive simulation. We embed this matched-prior principle in a three-step workflow and evaluate it via simulation: (1) identify matched priors, (2) evaluate prior predictive distributions, (3) calibrate Bayes factors and compare to the JZS/Cauchy default. For logistic regression, the matched Logistic(0, 0.75) intercept prior and matched Logistic effect priors with scale 0.25 to 0.30 provide well-calibrated Bayes factors. A signal detection analysis shows that prior scale is a criterion parameter: it shifts the operating point on the ROC curve but does not change discriminability. The advantage of the matched-prior workflow is principled scale selection on the probability scale, where effect sizes are directly interpretable. The workflow extends naturally to hierarchical models, where the prior on the random-effects variance has negligible influence on Bayes factors for fixed effects. Ready-to-use brms code and scaling formulas for any contrast coding are provided.",
    "doi": "",
    "preprint_doi": "",
    "subjects": [
      [
        {
          "id": "5b4e7425c6983001430b6c1e",
          "text": "Social and Behavioral Sciences"
        },
        {
          "id": "5b4e7426c6983001430b6c41",
          "text": "Quantitative Methods"
        },
        {
          "id": "5b4e7427c6983001430b6c92",
          "text": "Statistical Methods"
        }
      ]
    ],
    "link": "https://osf.io/preprints/psyarxiv/q7byw_v2/"
  },
  {
    "osf_id": "4byd3_v1",
    "title": "Effects of Cognitive Warmup on Cognitive Performance",
    "date_created": "2026-07-02T15:23:20.048471",
    "date_modified": "2026-07-03T09:15:20.917293",
    "description": "Cognitive performance is composed of a relatively stable cognitive ability (trait) and transient factors (state). While the trait can be influenced by long-term training, transient factors can be manipulated to achieve short-term improvements. Acute physical exercise has shown to improve subsequent cognitive performance through a warm-up effect; however, it remains unclear whether a similar enhancement can be achieved through cognitive activity itself. The present study investigated whether a brief cognitive warm-up could influence subsequent performance on a neuropsychological measure of processing speed. Forty healthy young adults participated in two experimental sessions and were assigned either to a cognitive warm-up group or a no-warm-up control group. The warm-up consisted of a brief series of serious games targeting executive functions and attention. Cognitive performance was assessed using the Symbol Digit Modalities Test (SDMT). Bayesian analyses indicated an interaction between session and group, with better results for the warm-up group in the active session with respect to the control group, net of scores in Raven’s Matrices. These findings provide preliminary evidence that a brief cognitive warm-up may enhance subsequent performance on a speeded cognitive task. Importantly, the effect emerged in the absence of task-specific priming and did not rely on physical exercise, suggesting that cognitive performance may be influenced through transient modulation of cognitive state. Further research employing active control conditions, larger samples, and direct measures of underlying mechanisms is needed to establish the robustness and specificity of this effect.",
    "doi": "",
    "preprint_doi": "",
    "subjects": [
      [
        {
          "id": "5b4e7425c6983001430b6c1e",
          "text": "Social and Behavioral Sciences"
        },
        {
          "id": "5b4e7425c6983001430b6c1f",
          "text": "Clinical Psychology"
        },
        {
          "id": "5b4e7426c6983001430b6c38",
          "text": "Clinical Neuropsychology"
        }
      ],
      [
        {
          "id": "5b4e7425c6983001430b6c1e",
          "text": "Social and Behavioral Sciences"
        },
        {
          "id": "5b4e7427c6983001430b6c8c",
          "text": "Cognitive Psychology"
        },
        {
          "id": "5b4e7428c6983001430b6cd5",
          "text": "Attention"
        }
      ]
    ],
    "link": "https://osf.io/preprints/psyarxiv/4byd3_v1/"
  },
  {
    "osf_id": "5n64t_v4",
    "title": "Working with Circular Data: A Tutorial for Cognitive and Behavioral Research",
    "date_created": "2026-07-02T15:33:00.056995",
    "date_modified": "2026-07-03T09:56:33.297886",
    "description": "Introductory statistics courses and conventional methods in behavioral and cognitive science are typically restricted to Euclidean space without explicitly stating this, leaving many researchers unaware of how to handle data with circular or periodic properties (e.g., time of day or orientation on a screen). This tutorial provides an accessible yet rigorous introduction, designed to bridge the gap between statistical theory and practical application. After discussing different ways of representing circular data mathematically and fundamental principles for working with them, we explain angular and vector representations and operations, including key considerations for implementing them in computer code. We then survey methods for visualizing circular data, including linear and polar plots and presentation of summary statistics. Next, we introduce circular measures of central tendency, dispersion, and shape: how they relate to their Euclidean counterparts, and why they differ. Finally, we turn to more advanced topics of the kind needed to construct models of circular data. We introduce the most common circular distribution families, including circular analogs of the Gaussian distribution and their properties, as well as flexible distribution families that can describe skewed and heavy-tailed data. We survey common applications in the supplementary materials. The tutorial takes a method-oriented approach, not tied to specific software, but highlighting factors relevant to experimental design, data analysis, and statistical modeling. A consistent theme is the need to rigorously account for the inherent periodicity of circular data. We also provide a consistent notation for circular statistics and parameters, addressing the lack of established conventions in the field.",
    "doi": "",
    "preprint_doi": "",
    "subjects": [
      [
        {
          "id": "5b4e7425c6983001430b6c1b",
          "text": "Neuroscience"
        }
      ],
      [
        {
          "id": "5b4e7425c6983001430b6c1e",
          "text": "Social and Behavioral Sciences"
        },
        {
          "id": "5b4e7426c6983001430b6c41",
          "text": "Quantitative Methods"
        }
      ]
    ],
    "link": "https://osf.io/preprints/psyarxiv/5n64t_v4/"
  },
  {
    "osf_id": "jw7ze_v2",
    "title": "Multi-System Brain-Body Mechanisms of Mental Health in Long-Term Meditation: Toward a Science of Advanced Meditation",
    "date_created": "2026-07-02T17:57:13.686748",
    "date_modified": "2026-07-03T10:13:16.939530",
    "description": "Most research on meditation and mental health has focused on short-term interventions in\nnovice populations, leaving the cumulative effects of long-term and advanced practice\nunderexplored. Advanced meditation is defined as states, stages, and endpoints that arise with the\nmaturation and mastery of mental-activity skills. This systematic review synthesizes evidence from\n52 studies across four databases, examining mental health outcomes through an integrative brain–\nbody lens.\nSix interrelated domains emerged: (1) well-being, (2) interpersonal functioning, (3) emotion\nregulation, (4) sensory–affective uncoupling of pain, (5) stress resilience, and (6) psychiatric\nsymptom prevention. Rather than operating independently, these domains reflect a coordinated,\nmulti-system adaptive response. Long-term meditation is consistently linked to enhanced\nattentional control, reduced emotional reactivity, and increased compassion, changes supported by\nfunctional and structural neuroplasticity in default-mode, salience, and frontoparietal networks.\nEmerging evidence further suggests that advanced practitioners may exhibit qualitatively distinct\nneural patterns, including reduced self-referential processing and concentration-related states.\nEvidence points to benefits beyond the brain. These neural changes are paralleled by\nsystemic adaptations: modulation of the hypothalamic–pituitary–adrenocortical axis,\ndownregulation of inflammatory gene expression, and upregulation of neuroplasticity-related\nmolecular markers.\nTogether, these findings support a holistic framework in which sustained meditation\nstrengthens interconnected neural, endocrine, immune, and cellular systems that collectively\nsupport mental health and resilience. Meditation is therefore best understood not as a purely\ncognitive technique but as a systemic brain–body intervention. Future research should prioritize\nlongitudinal, mechanistic designs and move beyond duration-based definitions toward skill-based\ncharacteriza",
    "doi": "",
    "preprint_doi": "",
    "subjects": [
      [
        {
          "id": "5b4e7424c6983001430b6c18",
          "text": "Psychiatry"
        }
      ],
      [
        {
          "id": "5b4e7425c6983001430b6c21",
          "text": "Life Sciences"
        }
      ],
      [
        {
          "id": "5b4e7425c6983001430b6c1b",
          "text": "Neuroscience"
        },
        {
          "id": "5b4e7425c6983001430b6c23",
          "text": "Cognitive Neuroscience"
        }
      ],
      [
        {
          "id": "5b4e7425c6983001430b6c1b",
          "text": "Neuroscience"
        },
        {
          "id": "5b4e7426c6983001430b6c4a",
          "text": "Molecular and Cellular Neuroscience"
        }
      ],
      [
        {
          "id": "5b4e7425c6983001430b6c1b",
          "text": "Neuroscience"
        },
        {
          "id": "5b4e7426c6983001430b6c68",
          "text": "Clinical Neuroscience"
        }
      ],
      [
        {
          "id": "5b4e7425c6983001430b6c1b",
          "text": "Neuroscience"
        },
        {
          "id": "5b4e7427c6983001430b6c77",
          "text": "Behavioral Neuroscience"
        }
      ]
    ],
    "link": "https://osf.io/preprints/psyarxiv/jw7ze_v2/"
  },
  {
    "osf_id": "drtvb_v1",
    "title": "What is Evaluative Conditioning Anyway? A Response to De Houwer (2026)",
    "date_created": "2026-07-02T19:18:37.418093",
    "date_modified": "2026-07-02T19:42:11.005014",
    "description": "We respond to De Houwer's (2026) commentary on our preprint (Corneille et al., 2026). In that preprint, we proposed a new definition of the Evaluative Conditioning effect (ECe) to address what we see as limitations in how ECe is currently conceptualized and studied. In the present response, we discuss substantive agreements and disagreements with De Houwer's commentary and clarify apparent misunderstandings on both sides. In doing so, we argue that our proposed definition withstands De Houwer's counter-arguments and offers a sensible alternative to existing definitions. More broadly, we believe that this exchange highlights important conceptual, methodological, and measurement-related questions whose resolution may have far-reaching implications for EC research. We hope that the discussion of these issues lives on beyond this exchange and helps move the field forward.",
    "doi": "",
    "preprint_doi": "",
    "subjects": [
      [
        {
          "id": "5b4e7425c6983001430b6c1e",
          "text": "Social and Behavioral Sciences"
        },
        {
          "id": "5b4e7426c6983001430b6c42",
          "text": "Consumer Psychology"
        }
      ],
      [
        {
          "id": "5b4e7425c6983001430b6c1e",
          "text": "Social and Behavioral Sciences"
        },
        {
          "id": "5b4e7425c6983001430b6c34",
          "text": "Social and Personality Psychology"
        },
        {
          "id": "5b4e7427c6983001430b6c6d",
          "text": "Social Cognition"
        }
      ],
      [
        {
          "id": "5b4e7425c6983001430b6c1e",
          "text": "Social and Behavioral Sciences"
        },
        {
          "id": "5b4e7427c6983001430b6c7e",
          "text": "Animal Learning and Behavior"
        }
      ],
      [
        {
          "id": "5b4e7425c6983001430b6c1e",
          "text": "Social and Behavioral Sciences"
        },
        {
          "id": "5b4e7427c6983001430b6c8c",
          "text": "Cognitive Psychology"
        }
      ],
      [
        {
          "id": "5b4e7425c6983001430b6c1e",
          "text": "Social and Behavioral Sciences"
        },
        {
          "id": "5b4e7425c6983001430b6c34",
          "text": "Social and Personality Psychology"
        },
        {
          "id": "5b4e7427c6983001430b6c94",
          "text": "Social Influence"
        }
      ],
      [
        {
          "id": "5b4e7425c6983001430b6c1e",
          "text": "Social and Behavioral Sciences"
        },
        {
          "id": "5b4e7425c6983001430b6c34",
          "text": "Social and Personality Psychology"
        },
        {
          "id": "5b4e7428c6983001430b6cd6",
          "text": "Attitudes and Persuasion"
        }
      ]
    ],
    "link": "https://osf.io/preprints/psyarxiv/drtvb_v1/"
  },
  {
    "osf_id": "c7x4s_v1",
    "title": "What Makes a Habit? Investigating Potential Determinants of Habit Formation",
    "date_created": "2026-07-03T07:37:36.392689",
    "date_modified": "2026-07-03T08:53:19.303979",
    "description": "Habitual behaviors are automatic responses to specific cues, acquired through repetition in stable contexts. While habits can support long-term behavior change, relatively little is known about which factors influence their development. We conducted a preregistered reanalysis of a six-month longitudinal study on habit formation during the COVID-19 pandemic. Participants (N = 254) completed monthly surveys assessing behavioral automaticity (i.e., habit) and ten potential determinants. Cluster analyses revealed two trajectories: habit formation and habit degradation, with cluster membership differing by behavioral complexity, frequency, and context stability. Multilevel models showed that six determinants were significantly associated with habit strength: autonomous motivation, behavior frequency, context stability, feeling energized, feeling pleased (positive), and perceived difficulty (negative). A significant interaction between time and behavior frequency emerged after correcting for multiple testing. Findings underscore the dynamic nature of habits and suggest that tailored interventions may be especially important during early formation and to prevent later degradation.",
    "doi": "10.1177/01461672261440446",
    "preprint_doi": "",
    "subjects": [
      [
        {
          "id": "5b4e7425c6983001430b6c1e",
          "text": "Social and Behavioral Sciences"
        },
        {
          "id": "5b4e7425c6983001430b6c34",
          "text": "Social and Personality Psychology"
        }
      ],
      [
        {
          "id": "5b4e7425c6983001430b6c1e",
          "text": "Social and Behavioral Sciences"
        },
        {
          "id": "5b4e7427c6983001430b6c93",
          "text": "Health Psychology"
        }
      ]
    ],
    "link": "https://osf.io/preprints/psyarxiv/c7x4s_v1/"
  },
  {
    "osf_id": "e87ft_v3",
    "title": "Exploring diagnosis of Developmental Coordination Disorder and  Specific Developmental Disorder of Motor Function: a secondary data analysis using Connected Bradford",
    "date_created": "2026-07-03T08:06:51.372480",
    "date_modified": "2026-07-03T09:04:42.534004",
    "description": "Background: Approximately 5% of children are affected by a neurodevelopmental disorder of their sensorimotor skills. DSM-V and ICD-10, the two most widely used classifications systems, define this diagnostically as either ‘Developmental Coordination Disorder’ (DCD) or ‘Specific Developmental Disorder of Motor Function’ (SDDMF, respectively). Being diagnosed with DCD/SDDMF has been found to have a detrimental impact on long-term health and education outcomes. Research repeatedly highlights parental dissatisfaction with the pathways for assessment and support of DCD/SDDMF, however, there has been a lack of research quantitatively exploring the diagnostic landscape. This study therefore aimed to evaluate the incidence of DCD/SDDMF in a diverse District (Bradford, UK) from 1950 -December 2024. Methods: Clinical codes related to sensorimotor skill assessments and diagnoses were searched for within the Connected Bradford dataset, which houses routinely collected primary and secondary healthcare data for over 800,000 residents. Results: There are 182,978 children currently in the Connected Bradford primary care records, suggesting there should be ~9149 children with a diagnosis (given estimated prevalence rates of 5%). But over 74 years of records available, there were only 152 recorded childhood diagnoses of SDDMF (the ICD-10 used in the UK and Europe for diagnosis). When exploring related diagnoses and findings there were 1037 cases (~14 per year), however this amount over 74 years is still nine times lower than would be expected within current childhood populations in Bradford. Moreover, there were low levels of recorded assessments and a lack of clarity regarding how children are being assessed. Conclusion: Diagnosis is the current pathway to accessing support across UK services, yet the current study highlights that children with DCD/SDDMF are not being diagnosed within Bradford. This likely reflects national and international challenges. Further research is needed to",
    "doi": "",
    "preprint_doi": "",
    "subjects": [
      [
        {
          "id": "5b4e7425c6983001430b6c1e",
          "text": "Social and Behavioral Sciences"
        },
        {
          "id": "5b4e7425c6983001430b6c2d",
          "text": "Developmental Psychology"
        }
      ]
    ],
    "link": "https://osf.io/preprints/psyarxiv/e87ft_v3/"
  },
  {
    "osf_id": "f6u2q_v1",
    "title": "Beyond search: solution-driven representation in human problem solving",
    "date_created": "2026-07-03T20:27:08.380057",
    "date_modified": "2026-07-04T12:37:55.856163",
    "description": "Cognitive science has often characterized problem solving as search or planning within a well-defined representation. Recent accounts extend this view by treating representation construction itself as search over possible construals, guided by downstream plan utility or collisions during simulation. Yet when relevant features, actions, and constraints are unbounded, this bilevel search over representations and solutions may be computationally intractable. Drawing on field studies of naturalistic decision-making and design, we propose that people instead adopt solution-driven strategies: familiar candidate solutions are retrieved early and used to determine which problem features must be represented. Across three preregistered experiments spanning spatial navigation, abstract compositional reasoning, and cost-based itinerary planning, increasing representational demands increased reuse of familiar but suboptimal solutions. This reuse was not blind perseveration: participants selectively represented information needed to evaluate candidate solutions. Process tracing further showed that information search was centered on cached routes, yet less ordered along the route itself, consistent with holistic evaluation rather than biased incremental search. These findings suggest that solution-driven cognition is central to problem solving under large-world representational complexity.",
    "doi": "",
    "preprint_doi": "",
    "subjects": [
      [
        {
          "id": "5b4e7425c6983001430b6c1e",
          "text": "Social and Behavioral Sciences"
        },
        {
          "id": "5b4e7426c6983001430b6c41",
          "text": "Quantitative Methods"
        },
        {
          "id": "5b4e7426c6983001430b6c4e",
          "text": "Mathematical Psychology"
        }
      ],
      [
        {
          "id": "5b4e7425c6983001430b6c1e",
          "text": "Social and Behavioral Sciences"
        },
        {
          "id": "5b4e7426c6983001430b6c41",
          "text": "Quantitative Methods"
        },
        {
          "id": "5b4e7426c6983001430b6c55",
          "text": "Computational Modeling"
        }
      ],
      [
        {
          "id": "5b4e7425c6983001430b6c1e",
          "text": "Social and Behavioral Sciences"
        },
        {
          "id": "5b4e7427c6983001430b6c8c",
          "text": "Cognitive Psychology"
        },
        {
          "id": "5b4e7427c6983001430b6c9b",
          "text": "Problem Solving"
        }
      ],
      [
        {
          "id": "5b4e7425c6983001430b6c1e",
          "text": "Social and Behavioral Sciences"
        },
        {
          "id": "5b4e7427c6983001430b6c8c",
          "text": "Cognitive Psychology"
        },
        {
          "id": "5b4e7427c6983001430b6ca5",
          "text": "Memory"
        }
      ],
      [
        {
          "id": "5b4e7425c6983001430b6c1e",
          "text": "Social and Behavioral Sciences"
        },
        {
          "id": "5b4e7426c6983001430b6c41",
          "text": "Quantitative Methods"
        },
        {
          "id": "5b4e7428c6983001430b6caf",
          "text": "Quantitative Psychology"
        }
      ],
      [
        {
          "id": "5b4e7425c6983001430b6c1e",
          "text": "Social and Behavioral Sciences"
        },
        {
          "id": "5b4e7427c6983001430b6c8c",
          "text": "Cognitive Psychology"
        },
        {
          "id": "5b4e7428c6983001430b6cd0",
          "text": "Creativity"
        }
      ],
      [
        {
          "id": "5b4e7425c6983001430b6c1e",
          "text": "Social and Behavioral Sciences"
        },
        {
          "id": "5b4e7427c6983001430b6c8c",
          "text": "Cognitive Psychology"
        },
        {
          "id": "5b4e7429c6983001430b6cf5",
          "text": "Biases, Framing, and Heuristics"
        }
      ],
      [
        {
          "id": "5b4e7425c6983001430b6c1e",
          "text": "Social and Behavioral Sciences"
        },
        {
          "id": "5b4e7427c6983001430b6c8c",
          "text": "Cognitive Psychology"
        },
        {
          "id": "5b4e7429c6983001430b6cfa",
          "text": "Reasoning"
        }
      ],
      [
        {
          "id": "5b4e7425c6983001430b6c1e",
          "text": "Social and Behavioral Sciences"
        },
        {
          "id": "5b4e7427c6983001430b6c8c",
          "text": "Cognitive Psychology"
        },
        {
          "id": "5b4e7429c6983001430b6cfb",
          "text": "Judgment and Decision Making"
        }
      ]
    ],
    "link": "https://osf.io/preprints/psyarxiv/f6u2q_v1/"
  },
  {
    "osf_id": "h9m8e_v1",
    "title": "Beyond Aggregate Accuracy: A Bayesian Time-Varying Autoregressive Model and Its Multilevel Extension",
    "date_created": "2026-07-03T20:56:59.039555",
    "date_modified": "2026-07-04T12:37:10.295127",
    "description": "Autoregressive (AR) models are widely used to study within-person dynamics in intensive longitudinal data (ILD), but they assume constant parameters, an assumption that may not hold when the dynamics change, as during development, intervention, or recovery. The time-varying autoregressive (TV-AR) model accommodates such change by representing the intercept and AR coefficient as smooth functions of time. As originally proposed, however, it was developed for a single individual and evaluated with time-averaged accuracy metrics. We address these limitations by extending it to a Bayesian multilevel formulation with population-average and individual-specific time-varying parameters, and by emphasizing pointwise evaluation of accuracy rather than aggregate accuracy alone. Two simulation studies examined how well the single-level and multilevel models recover time-varying dynamics. Examining bias at each time point, we found that it was largest near the series boundaries and in regions of steep change or high curvature. The time-varying intercept and AR coefficient showed complementary biases that largely cancelled in the implied mean, which was therefore recovered with smaller bias. In the multilevel model, the best allocation between persons and time points depended on the parameter and inferential level: the AR coefficient favored longer series at both levels, whereas the implied mean favored more persons for population-average recovery but longer series for individual recovery. We discuss implications and recommendations for study design, result interpretation, and model selection.",
    "doi": "",
    "preprint_doi": "",
    "subjects": [
      [
        {
          "id": "5b4e7425c6983001430b6c1e",
          "text": "Social and Behavioral Sciences"
        },
        {
          "id": "5b4e7426c6983001430b6c41",
          "text": "Quantitative Methods"
        }
      ]
    ],
    "link": "https://osf.io/preprints/psyarxiv/h9m8e_v1/"
  },
  {
    "osf_id": "7rg83_v4",
    "title": "Examining Linking Language and Causal Implications in Observational Psychological Capital Research",
    "date_created": "2026-07-03T21:13:35.384165",
    "date_modified": "2026-07-04T12:36:31.185312",
    "description": "The present study examines whether the issues with implied causal inference identified by Haber et al. (2022) in observational health research extend to the field of industrial-organisational (IO) psychology. Haber et al. found that causal relationships were implied through the language used to link exposures and outcomes and through recommendations for action. This small-scale conceptual replication applies Haber et al.’s approach to psychological capital (PsyCap), an increasingly popular construct in the domain of IO psychology. Specifically, we evaluate the causal strength of the language used to describe the nature of the connection between given variables when reporting findings and when making recommendations for action in 50 PsyCap articles. The majority of action recommendations were found to have strong causal implications (85% in abstracts, 84% in discussion sections), and most linking sentences implied some level of causality (64% in abstracts, 58% in discussion sections). This was despite very few articles explicitly stating an intention to estimate causal effects (10%) and many explicitly warning against drawing causal inferences (42%). No significant relationship was found between the causality implied in the linking sentences and the strength of causal implication of the action recommendations. These findings have important implications for how research is implemented, and very real consequences for those who are the focus of such implementations. Increased transparency about causal interests and reasoning is needed to uphold the credibility of findings and the integrity of applications of observational PsyCap research.",
    "doi": "",
    "preprint_doi": "",
    "subjects": [
      [
        {
          "id": "5b4e7424c6983001430b6c19",
          "text": "Meta-science"
        }
      ],
      [
        {
          "id": "5b4e7425c6983001430b6c1e",
          "text": "Social and Behavioral Sciences"
        },
        {
          "id": "5b4e7425c6983001430b6c22",
          "text": "Industrial and Organizational Psychology"
        }
      ]
    ],
    "link": "https://osf.io/preprints/psyarxiv/7rg83_v4/"
  },
  {
    "osf_id": "6ye42_v1",
    "title": "From suspicion to violent action: A multi-category framework of fear speech using qualitative content analysis and machine learning",
    "date_created": "2026-07-04T07:12:01.267844",
    "date_modified": "2026-07-04T12:20:29.588253",
    "description": "Current online hate speech flagging systems overlook more subtle forms of dangerous content that are not overtly violent, and more akin to what has been described as fear speech. Fear plays a crucial role in the process of radicalisation (Doosje et al., 2013), and is an important motivator of violence (Buyse, 2014). Yet, very little work has directly examined types and variations of online fear speech. In Study 1, we qualitatively content analysed a pre-annotated fear speech dataset to propose a novel framework of fear speech classification. This framework highlights a range of varying intensities of fear messages (Suspicion, Non-Violent Fear, Violent Fear, Non-Violent Call to Action, and Violent Call to Action). In Study 2, we generated synthetic data corresponding to our proposed framework, and used it to train a lightweight transformer-based model using contrastive learning, to enable automatic multilabel classification of fear speech. Our model outperformed multiple baselines, showing a decent ability to detect and classify fear speech. The proposed framework extends theorisation on hate speech and can be used to automatically detect less obvious harmful speech online, inform moderation policies and develop more appropriate counter fear-speech designs.",
    "doi": "",
    "preprint_doi": "",
    "subjects": [
      [
        {
          "id": "5b4e7425c6983001430b6c1e",
          "text": "Social and Behavioral Sciences"
        }
      ]
    ],
    "link": "https://osf.io/preprints/psyarxiv/6ye42_v1/"
  }
]
